e2m/__init__.py
e2m/e2m.png
e2m/main.py
e2m-1.0.3.dist-info/entry_points.txt
e2m-1.0.3.dist-info/WHEEL
e2m-1.0.3.dist-info/METADATA
e2m-1.0.3.dist-info/RECORD
