Metadata-Version: 2.1
Name: e2m
Version: 1.0.3
Summary: Email to maildir sync
Home-page: https://github.com/paul-nameless/e2m
License: UNKNOWN
Author: Paul Nameless
Author-email: paul.nameless@icloud.com
Requires-Python: >=3.5
Classifier: Programming Language :: Python :: 3
Classifier: Programming Language :: Python :: 3.7
Provides-Extra: .none
